spartaquant/__init__.py
spartaquant/getBBMData.py
spartaquant-1.0.7.dist-info/LICENSE
spartaquant-1.0.7.dist-info/METADATA
spartaquant-1.0.7.dist-info/WHEEL
spartaquant-1.0.7.dist-info/top_level.txt
spartaquant-1.0.7.dist-info/RECORD
