Metadata-Version: 2.1
Name: spartaquant
Version: 1.0.7
Summary: SpartaQuant Python API
Home-page: https://spartaquant.com
Author: Benjamin Meyer
Author-email: spartaquant@gmail.com
License: UNKNOWN
Platform: UNKNOWN
Classifier: Programming Language :: Python :: 3
Classifier: License :: OSI Approved :: MIT License
Classifier: Operating System :: OS Independent
Requires-Python: >=3.6
License-File: LICENSE
